linkedlistx/CLL.py
linkedlistx/DCLL.py
linkedlistx/DLL.py
linkedlistx/SLL.py
linkedlistx/__init__.py
linkedlistx/node.py
linkedlistx-0.1.0.dist-info/licenses/LICENSE
linkedlistx-0.1.0.dist-info/METADATA
linkedlistx-0.1.0.dist-info/WHEEL
linkedlistx-0.1.0.dist-info/top_level.txt
linkedlistx-0.1.0.dist-info/RECORD
