Metadata-Version: 2.4
Name: linkedlistx
Version: 0.1.0
Summary: A Python package implementing singly, doubly, circular singly, and circular doubly linked lists.
Author-email: Aswath <aswathnag.s@gmail.com>
License: MIT
Keywords: linked list,data structures,python,sll,dll,cll,dcll
Classifier: Programming Language :: Python :: 3
Classifier: Programming Language :: Python :: 3.8
Classifier: License :: OSI Approved :: MIT License
Classifier: Operating System :: OS Independent
Classifier: Topic :: Software Development :: Libraries :: Python Modules
Classifier: Intended Audience :: Developers
Classifier: Development Status :: 3 - Alpha
Requires-Python: >=3.7
License-File: LICENSE
Dynamic: license-file
